LICENSE
convert_labse_tf_pt/__init__.py
convert_labse_tf_pt/configurations.py
convert_labse_tf_pt/convert.py
convert_labse_tf_pt/data/labse_vocab/cased_vocab.txt
convert_labse_tf_pt/data/smaller_vocab/vocab-en-fr-es-de-zh-ar-zh_classical-it-ja-ko-nl-pl-pt-th-tr-ru.txt
convert_labse_tf_pt-3.0.0.dist-info/LICENSE
convert_labse_tf_pt-3.0.0.dist-info/METADATA
convert_labse_tf_pt-3.0.0.dist-info/WHEEL
convert_labse_tf_pt-3.0.0.dist-info/entry_points.txt
convert_labse_tf_pt-3.0.0.dist-info/RECORD
