Metadata-Version: 2.1
Name: convert-labse-tf-pt
Version: 3.0.0
Summary: Convert LaBSE model from TensorFlow to PyTorch.
Home-page: https://github.com/setu4993/convert-labse-tf-pt
License: MIT
Keywords: transformers,bert,labse,pytorch,tensorflow
Author: Setu Shah
Author-email: setu+labse@setu.me
Requires-Python: >=3.8,<3.11
Classifier: License :: OSI Approved :: MIT License
Classifier: Programming Language :: Python :: 3
Classifier: Programming Language :: Python :: 3.8
Classifier: Programming Language :: Python :: 3.9
Classifier: Programming Language :: Python :: 3.10
Requires-Dist: ipywidgets (>=7.6.3,<8.0.0)
Requires-Dist: loguru (>=0.6.0,<0.7.0)
Requires-Dist: safetensors (>=0.3.1,<0.4.0)
Requires-Dist: tensorflow-hub (>=0.12.0,<0.13.0)
Requires-Dist: tensorflow-text (<2.9.0)
Requires-Dist: transformers[flax,sentencepiece,tf,torch] (>=4.29.2,<4.30.0)
Project-URL: Repository, https://github.com/setu4993/convert-labse-tf-pt
